df1/__init__.py
df1/file_type.py
df1/sts_codes.py
df1/commands/__init__.py
df1/commands/base_command.py
df1/commands/commands.py
df1/models/__init__.py
df1/models/base_data_frame.py
df1/models/base_frame.py
df1/models/base_plc.py
df1/models/crc16.py
df1/models/df1_base.py
df1/models/df1_plc.py
df1/models/df1_serial_client.py
df1/models/df1_serial_plc.py
df1/models/df1_tcp_client.py
df1/models/df1_tcp_plc.py
df1/models/frame_factory.py
df1/models/receive_buffer.py
df1/models/reply_timeout.py
df1/models/tx_symbol.py
df1/models/exceptions/__init__.py
df1/models/exceptions/send_queue_overflow_error.py
df1/models/exceptions/send_receive_error.py
df1/models/exceptions/thread_error.py
df1/replies/__init__.py
df1/replies/base_simple_reply.py
df1/replies/reply_4f.py
df1/replies/reply_ack.py
df1/replies/reply_enq.py
df1/replies/reply_nak.py
df1py3-1.0a45.dist-info/DESCRIPTION.rst
df1py3-1.0a45.dist-info/METADATA
df1py3-1.0a45.dist-info/RECORD
df1py3-1.0a45.dist-info/WHEEL
df1py3-1.0a45.dist-info/metadata.json
df1py3-1.0a45.dist-info/top_level.txt
