Metadata-Version: 2.0
Name: df1py3
Version: 1.0a45
Summary: A basic DF1 implementation in Python3
Home-page: https://github.com/reyanvaldes/Df1
Author: Jerther,rvaldes
Author-email: jtheriault@metalsartigan.com, rvaldes@itgtec.com
License: MIT License
Platform: UNKNOWN
